LICENSE
README.md
setup.cfg
setup.py
dconstruct/__init__.py
dconstruct.egg-info/PKG-INFO
dconstruct.egg-info/SOURCES.txt
dconstruct.egg-info/dependency_links.txt
dconstruct.egg-info/top_level.txt
tests/__init__.py
tests/test_basic.py