Metadata-Version: 2.1
Name: dconstruct
Version: 1.0.0
Summary: Extremely simple way to build objects from a dictionary specification, recursively.
Home-page: https://github.com/kavigupta/dconstruct
Author: Kavi Gupta
Author-email: dconstruct@kavigupta.org
Project-URL: Documentation, https://dconstruct.readthedocs.io/en/latest/#
Classifier: Programming Language :: Python :: 3.9
Classifier: Programming Language :: Python :: 3.10
Classifier: Programming Language :: Python :: 3.11
Classifier: Programming Language :: Python :: 3.12
Classifier: Operating System :: OS Independent
Requires-Python: >=3.9
License-File: LICENSE
